{
    "issue_number": 275,
    "updated_at": "2026-03-26T07:45:27.937Z",
    "faq": [
        {
            "question": "Why does the Home Connect API return `403 Forbidden` during authorisation?",
            "answer": "A `403 Forbidden` error during the `POST /security/oauth/device_authorization` request indicates that the Home Connect API servers are explicitly rejecting the connection from your network. This is typically caused by regional geo-blocking or service restrictions implemented by the provider (for example, in Russia).\n\nIf the Home Connect API is restricted in your region, the plugin will be unable to establish an initial connection or refresh authorisation tokens. This is a network-level restriction imposed by the service provider, and the plugin does not provide mechanisms to bypass these geo-blocks.",
            "semantic_abstract": "Home Connect API authorisation fails with a `403 Forbidden` error when requests originate from regions subject to network-level geo-blocking or service provider restrictions. This prevents the OAuth device flow from initiating because the API endpoint rejects the connection based on the source IP address before the plugin can establish a session.",
            "hash": "9b14639eb60559981bbaabe33e5c26bc4379cf7df323146929c0084ed6652607"
        }
    ]
}