{
    "issue_number": 382,
    "updated_at": "2026-04-14T11:43:20.113Z",
    "faq": [
        {
            "question": "Why does my fridge or freezer always show the door as Open in HomeKit even when it is closed?",
            "answer": "This behaviour is typically caused by appliance firmware failing to update the combined `DoorState` value in the Home Connect API, even if the appliance's internal sensors and door alarms are functioning correctly. \n\nIn accordance with the HomeKit Accessory Protocol Specification, the plugin maps the Home Connect API states as follows:\n* `Open`: `100%` (Open)\n* `Closed`: `0%` (Closed)\n* `Locked`: `0%` (Closed)\n\nIf your appliance is consistently reporting `Open` regardless of the physical door position, it is likely that the API is not emitting the necessary events. You can attempt the following workarounds:\n\n1. **Expose individual doors**: Refrigerator-class appliances often provide specific status values for individual compartments (e.g., `ChillerLeft`, `ChillerRight`, `FlexCompartment`, `Freezer`, or `Refrigerator`). Configure the plugin to expose these individual door services, as they may update correctly even when the combined status is stuck.\n2. **Verify with debug logs**: Enable the **Log Debug as Info** option in the plugin configuration to check the raw API values. If the API is reporting the state incorrectly, the issue lies with the appliance firmware or the Home Connect cloud service.\n3. **Contact Support**: If individual doors also fail to report correctly, contact [Home Connect Customer Service](https://www.home-connect.com/global/service/contact-customer-service/service) to request a firmware fix. You will need to provide your Home Connect account email and the appliance ID (`haID`).",
            "semantic_abstract": "Certain FridgeFreezer appliances (e.g. Thermador) exhibit firmware quirks where the aggregate `BSH.Common.Status.DoorState` fails to update via the Home Connect API despite physical state changes. This mismatch between internal door alarms and the exposed API status results in HomeKit incorrectly displaying a constant `Open` (100%) position, requiring the use of individual compartment door services as a workaround.",
            "hash": "3c33e4f581f101820fe6c05438dca0d568b8ff6ccb3495eb951dc69124a7e02f"
        }
    ]
}