{
    "issue_number": 385,
    "updated_at": "2026-04-30T11:53:32.691Z",
    "faq": [
        {
            "question": "Why does my freezer always show the door as open or report an incorrect `BSH.Common.Status.DoorState`?",
            "answer": "Some freezer models may incorrectly report the generic door status as `Open` via the Home Connect API, even when the door is physically closed. This is typically a firmware or API-level bug where the appliance provides the correct status only through a device-specific key (`Refrigeration.Common.Status.Door.Freezer`) rather than the standard one.\n\nTo resolve this, you must override the default door mapping in the plugin configuration for that specific appliance:\n1. Navigate to the appliance-specific settings in the plugin configuration.\n2. Disable the generic `Door` feature.\n3. Enable the `Freezer Door` feature.\n\nThis forces the plugin to monitor the specific freezer door state instead of the incorrect generic state. Affected users are encouraged to report this behaviour to Home Connect customer service with their appliance model and account details to assist in a permanent firmware fix.",
            "semantic_abstract": "A Home Connect API discrepancy causes certain freezer models to report an incorrect generic door status, necessitating a configuration override to use the appliance-specific `Freezer Door` state for accurate HomeKit reporting. This mismatch between the generic `BSH.Common.Status.DoorState` and the specific `Refrigeration.Common.Status.Door.Freezer` state typically stems from appliance firmware quirks.",
            "hash": "2b1898baeb2a746c95028dbcfb000c7d92c7df58b897ec6bfa340e57b9f9dd6b"
        }
    ]
}